spaceone/__init__.py
spaceone/inventory_v2/__init__.py
spaceone/inventory_v2/conf/__init__.py
spaceone/inventory_v2/conf/collector_conf.py
spaceone/inventory_v2/conf/global_conf.py
spaceone/inventory_v2/error/__init__.py
spaceone/inventory_v2/error/asset.py
spaceone/inventory_v2/error/collector.py
spaceone/inventory_v2/error/region.py
spaceone/inventory_v2/info/__init__.py
spaceone/inventory_v2/info/common_info.py
spaceone/inventory_v2/info/region_info.py
spaceone/inventory_v2/interface/__init__.py
spaceone/inventory_v2/interface/grpc/__init__.py
spaceone/inventory_v2/interface/grpc/collector.py
spaceone/inventory_v2/interface/grpc/metric.py
spaceone/inventory_v2/interface/grpc/metric_data.py
spaceone/inventory_v2/interface/grpc/metric_example.py
spaceone/inventory_v2/interface/grpc/region.py
spaceone/inventory_v2/interface/task/__init__.py
spaceone/inventory_v2/interface/task/v1/__init__.py
spaceone/inventory_v2/interface/task/v1/inventory_scheduler.py
spaceone/inventory_v2/lib/__init__.py
spaceone/inventory_v2/lib/resource_manager.py
spaceone/inventory_v2/lib/rule_matcher.py
spaceone/inventory_v2/manager/__init__.py
spaceone/inventory_v2/manager/asset_manager.py
spaceone/inventory_v2/manager/collecting_manager.py
spaceone/inventory_v2/manager/collection_state_manager.py
spaceone/inventory_v2/manager/collector_manager.py
spaceone/inventory_v2/manager/collector_plugin_manager.py
spaceone/inventory_v2/manager/collector_rule_manager.py
spaceone/inventory_v2/manager/identity_manager.py
spaceone/inventory_v2/manager/job_manager.py
spaceone/inventory_v2/manager/job_task_manager.py
spaceone/inventory_v2/manager/metric_data_manager.py
spaceone/inventory_v2/manager/metric_example_manager.py
spaceone/inventory_v2/manager/metric_manager.py
spaceone/inventory_v2/manager/plugin_manager.py
spaceone/inventory_v2/manager/region_manager.py
spaceone/inventory_v2/manager/repository_manager.py
spaceone/inventory_v2/manager/secret_manager.py
spaceone/inventory_v2/model/__init__.py
spaceone_inventory_v2-0.0.dev3.dist-info/METADATA
spaceone_inventory_v2-0.0.dev3.dist-info/WHEEL
spaceone_inventory_v2-0.0.dev3.dist-info/top_level.txt
spaceone_inventory_v2-0.0.dev3.dist-info/RECORD
