Metadata-Version: 2.1
Name: spaceone-inventory-v2
Version: 0.0.dev3
Summary: SpaceONE Inventory v2 service
Home-page: https://www.spaceone.dev/
Author: MEGAZONE SpaceONE Team
Author-email: admin@spaceone.dev
License: Apache License 2.0
Platform: UNKNOWN
Requires-Dist: spaceone-core
Requires-Dist: spaceone-api
